setup.py
gaussian_and_binomial_dist/Binomialdistribution.py
gaussian_and_binomial_dist/Gaussiandistribution.py
gaussian_and_binomial_dist/Generaldistribution.py
gaussian_and_binomial_dist/__init__.py
gaussian_and_binomial_dist.egg-info/PKG-INFO
gaussian_and_binomial_dist.egg-info/SOURCES.txt
gaussian_and_binomial_dist.egg-info/dependency_links.txt
gaussian_and_binomial_dist.egg-info/not-zip-safe
gaussian_and_binomial_dist.egg-info/top_level.txt