Metadata-Version: 1.0
Name: gaussian-and-binomial-dist
Version: 1.0
Summary: Gaussian and Binomial distributions
Home-page: UNKNOWN
Author: Jermaine Robinson
Author-email: jermaineprogrammer@gmail.com
License: UNKNOWN
Platform: UNKNOWN
